ryder/__init__.py
ryder/articles.py
ryder/clean.py
ryder/errors.py
ryder/sources.py
ryder/utils.py
ryder/ressources/headers.json
ryder/ressources/medias.fr
ryder/ressources/stop_urls.txt
ryder-0.0.4.dist-info/METADATA
ryder-0.0.4.dist-info/WHEEL
ryder-0.0.4.dist-info/top_level.txt
ryder-0.0.4.dist-info/RECORD
