Metadata-Version: 2.1
Name: ryder
Version: 0.0.4
Summary: News reader for Python
Home-page: https://github.com/kerighan/ryder
Author: Maixent Chenebaux
Author-email: max.chbx@gmail.com
License: UNKNOWN
Platform: UNKNOWN
Classifier: Programming Language :: Python :: 3
Classifier: Programming Language :: Python :: 3.7
Classifier: License :: OSI Approved :: MIT License
Classifier: Operating System :: OS Independent
Requires-Python: >=3.5
Requires-Dist: langdetect
Requires-Dist: dateparser
